odoo/addons/mrp_bom_warn_message/README.rst
odoo/addons/mrp_bom_warn_message/__init__.py
odoo/addons/mrp_bom_warn_message/__manifest__.py
odoo/addons/mrp_bom_warn_message/i18n/es.po
odoo/addons/mrp_bom_warn_message/models/__init__.py
odoo/addons/mrp_bom_warn_message/models/mrp_bom.py
odoo/addons/mrp_bom_warn_message/models/mrp_production.py
odoo/addons/mrp_bom_warn_message/security/mrp_bom_warn_message_security.xml
odoo/addons/mrp_bom_warn_message/static/description/icon.png
odoo/addons/mrp_bom_warn_message/views/mrp_bom_views.xml
odoo/addons/mrp_bom_warn_message/views/mrp_production_views.xml
odoo_addon_mrp_bom_warn_message-15.0.1.0.0.3.dist-info/METADATA
odoo_addon_mrp_bom_warn_message-15.0.1.0.0.3.dist-info/WHEEL
odoo_addon_mrp_bom_warn_message-15.0.1.0.0.3.dist-info/top_level.txt
odoo_addon_mrp_bom_warn_message-15.0.1.0.0.3.dist-info/RECORD
