Metadata-Version: 2.1
Name: odoo-addon-mrp_bom_warn_message
Version: 15.0.1.0.0.3
Requires-Python: >=3.8
Requires-Dist: odoo>=15.0a,<15.1dev
Summary: Add a configurable warning when a bill of materials is selected on a MRP manufacturing order.
Home-page: https://github.com/sygel-technology/sy-manufacturing
License: AGPL-3
Author: =?utf-8?q?Alberto_Mart=C3=ADnez=2C_Odoo_Community_Association_=28OCA=29?=
Author-email: support@odoo-community.org
Classifier: Programming Language :: Python
Classifier: Framework :: Odoo
Classifier: Framework :: Odoo :: 15.0
Classifier: License :: OSI Approved :: GNU Affero General Public License v3
